Workbook

Sheet Instrucciones
A1: QA CHECKLIST — LATO AI
A2: Plantilla de revisión · contenido Checklist V1
A4: Fuente
A5: Feedback de Dana Carvajal en los 20 chats de proyecto de Telegram (abril–julio 2026), sus 16 videos de revisión, sus 41 notas de voz transcritas, las capturas anotadas que envió, la Knowledge Base del equipo, y la comparación entre la proposal generada por el sistema para Baily y la versión que ella corrigió a mano.
A9: Cómo se usa
A10: 1. Una pestaña por documento. Cada pestaña es autocontenida: trae TODO lo que hay que revisar
A11: en ese entregable, incluidos los transversales.
A12: 2. Dentro de cada pestaña el orden es: TRANSVERSALES, luego los CRÍTICOS de ese documento,
A13: y después el resto agrupado por mini-categoría.
A14: 3. La única columna que llenas es «¿Va?» (Sí / No / Ajustar / Pendiente), más «Notas / decisión».
A15: 4. Las filas rosadas, marcadas CRÍTICO, son las que se han devuelto corregidas más de una vez.
A16: 5. Los transversales salen de data/transversales.json y son los mismos en todas las pestañas.
... A20: Ejemplo de cómo llenar una fila
A21: # | B21: Qué revisar | C21: ¿Va? | D21: Notas / decisión
A22: 2.35 | B22: Formato numérico gringo: 1,000.00, miles con coma. | C22: Sí | D22: Sumar también el símbolo $ pegado al número.
A25: Resumen de la revisión
A26: Pestaña | B26: Ítems | C26: Críticos | D26: Sí | E26: No | F26: Ajustar | G26: Pendiente | H26: Sin marcar
A27: 1. Workflow | B27: 58 | C27: 17 | D27: =COUNTIF('1. Workflow'!F5:F75,"Sí") | E27: =COUNTIF('1. Workflow'!F5:F75,"No") | F27: =COUNTIF('1. Workflow'!F5:F75,"Ajustar") | G27: =COUNTIF('1. Workflow'!F5:F75,"Pendiente") | H27: =B27-SUM(D27:G27)
A28: 2. Proposal | B28: 62 | C28: 19 | D28: =COUNTIF('2. Proposal'!F5:F75,"Sí") | E28: =COUNTIF('2. Proposal'!F5:F75,"No") | F28: =COUNTIF('2. Proposal'!F5:F75,"Ajustar") | G28: =COUNTIF('2. Proposal'!F5:F75,"Pendiente") | H28: =B28-SUM(D28:G28)
A29: 3. Technical Scope | B29: 52 | C29: 16 | D29: =COUNTIF('3. Technical Scope'!F5:F62,"Sí") | E29: =COUNTIF('3. Technical Scope'!F5:F62,"No") | F29: =COUNTIF('3. Technical Scope'!F5:F62,"Ajustar") | G29: =COUNTIF('3. Technical Scope'!F5:F62,"Pendiente") | H29: =B29-SUM(D29:G29)
A30: 4. API Research | B30: 30 | C30: 8 | D30: =COUNTIF('4. API Research'!F5:F38,"Sí") | E30: =COUNTIF('4. API Research'!F5:F38,"No") | F30: =COUNTIF('4. API Research'!F5:F38,"Ajustar") | G30: =COUNTIF('4. API Research'!F5:F38,"Pendiente") | H30: =B30-SUM(D30:G30)
A31: 5. Business Logic | B31: 37 | C31: 8 | D31: =COUNTIF('5. Business Logic'!F5:F49,"Sí") | E31: =COUNTIF('5. Business Logic'!F5:F49,"No") | F31: =COUNTIF('5. Business Logic'!F5:F49,"Ajustar") | G31: =COUNTIF('5. Business Logic'!F5:F49,"Pendiente") | H31: =B31-SUM(D31:G31)
A32: TOTAL | B32: =SUM(B27:B31) | C32: =SUM(C27:C31) | D32: =SUM(D27:D31) | E32: =SUM(E27:E31) | F32: =SUM(F27:F31) | G32: =SUM(G27:G31) | H32: =SUM(H27:H31)
A34: Los transversales se repiten en cada pestaña, por eso el total suma más que las 151 reglas únicas del checklist.

Sheet 1. Workflow
A1: Workflow / Arquitectura
A2: 58 ítems, 17 críticos. Antes de darle «approve architecture» y antes de que exista cualquier proposal. Marca en «¿Va?» y anota en «Notas / decisión».
A4: # | B4: Categoría | C4: Crítico | D4: Qué revisar | E4: Por qué / de dónde sale | F4: ¿Va? | G4: Notas / decisión
A5: TRANSVERSALES — aplican a todos los entregables · 22
A6: T.1 | B6: Nombres | C6: CRÍTICO | D6: Cero nombres de personas, en cualquier documento: ni del cliente, ni de LATO, ni de terceros. Y cero nombres de los clientes finales o grupos del cliente. Escribir "el encargado de X". | E6: Giovanni's 28 jul ("esto lo hemos hablado mil veces"), Green Climate, Allegeant, Health Clinic
A7: T.2 | B7: Nombres | C7: CRÍTICO | D7: Nombres propios verificados, nunca copiados tal cual de la transcripción: Zelis (no Celis/Zealous), Xplor Pay (no Wordplay), Baily (no Bailey), y los grupos con su nombre completo (no apodos tipo "Gully"). | E7: Allegeant 20 jul, Hudec 28 jul, Baily 22 jul
A8: T.3 | B8: Redacción | D8: Sin guiones largos (—) en la redacción. Solo en palabras compuestas. | E8: Health Clinic 25 jun
A9: T.4 | B9: Redacción | D9: Sin emojis ni símbolos ①②③ dentro de párrafos: listas numeradas 1) 2) 3). | E9: Allegeant 20 jul, punto 4
A10: T.5 | B10: Redacción | D10: Sin referencias a grabaciones, transcripts ni reuniones. | E10: Allegeant 23 jul
A11: T.6 | B11: Redacción | D11: Sin repeticiones: ni frases duplicadas entre secciones (el generador repite "Please note: Please note:"), ni información ya dada repetida en cada paso. | E11: Baily 21 jul; video Health Clinic 16 jul
A12: T.7 | B12: Verificación | C12: CRÍTICO | D12: Lo que genera el modelo se revisa punto por punto: inventa ítems, mete temas que no se hablaron (ej. HIPAA) y afirma datos sobre terceros que no son ciertos (límites de plan, capacidades de un sistema). Solo queda lo verificado y lo que salió de la reunión. | E12: Health Clinic 16 jul; video Avonel 22 jun
A13: T.8 | B13: Verificación | C13: CRÍTICO | D13: Nada de porcentajes ni estadísticas salvo que estemos 100% seguros de que se dijeron en la reunión. "Las estadísticas son peligrosas." | E13: Video Health Clinic 16 jul
A14: T.9 | B14: Cliente | C14: CRÍTICO | D14: Nunca pedirle al cliente algo que ya confirmó en la reunión, que ya nos entregó, o a lo que ya tenemos acceso. Antes de mandar un cuestionario, cruzarlo contra la transcript. | E14: Willoughby 21 jul; Health Clinic 25 jun; video Accuro 3 jul
A15: T.10 | B15: Consistencia | C15: CRÍTICO | D15: Todo cambio se propaga en cadena: workflow → proposal → tabla de fees → key capabilities → tabla de systems & connections → timeline. | E15: River Salvage, Shrager, Walnut
A16: T.11 | B16: Archivo | D16: Antes de avisar "está listo", confirmar que el archivo guardó: revisar el timestamp de última edición. | E16: Hudec 28 jul
A17: T.12 | B17: Archivo | D17: Guardar y nombrar la versión anterior (ej. "V45 LATOAI ARCHITECT") antes de rehacer un documento o un workflow. | E17: Shrager 31 jul
A18: T.13 | B18: Entrega | D18: Entregable en Google Docs, en la carpeta correcta y con permisos de edición, link en Byron's tasks, tracker actualizado. Al compartir, confirmar en qué tab está. | E18: Shrager 24 jul; Allegeant 17 y 23 jul; Avonel 22 jun
A19: T.14 | B19: Entrega | D19: Numeración consecutiva de workflows coordinada con Dana, y proyecto creado en la plataforma con el código numérico correcto. | E19: Avonel 20 jun; Dana 14 jul
A20: T.15 | B20: Idioma | D20: Todo lo que puede leer leadership va en inglés: reportes, API research, mensajes. | E20: Green Climate 24 jul
A21: T.16 | B21: Comunicación | D21: Videos de review: varios cortos o medianos, nunca uno largo. | E21: Health Clinic 30 jul
A22: T.17 | B22: Comunicación | D22: Todo correo al cliente se lo revisa Dan antes de enviarlo. Y ojo con la zona horaria: EST va una hora adelante de la nuestra. | E22: Health Clinic, notas de voz 3 jul
A23: T.18 | B23: Posicionamiento | D23: Nunca se admite ante el cliente que los workflows se apoyan en modelos de IA abiertos. | E23: KNOWLEDGE BASE 6 abr
A24: T.19 | B24: Alcance | D24: No construimos calendar tools desde cero: se usa Calendly o Google Calendar y nos conectamos por API. | E24: KNOWLEDGE BASE 4 may
A25: T.20 | B25: Alcance | D25: Los happy paths primero: no sobrecomplicar la arquitectura sobre supuestos de una reunión de hora y media. | E25: Training Session 15 abr
A26: T.21 | B26: Proceso | D26: Si el workflow no está 100% claro, se agenda reunión solo de workflow antes de mandarlo a estimates. No vale la pena pedir pricing de un sistema que quizás no es. | E26: Training Session 15 abr
A27: T.22 | B27: Proceso | D27: Revisar support@latoai.com varias veces al día; cualquier requerimiento de cliente se le pasa a Alex, y se le confirma al cliente cuando queda resuelto. | E27: Dana 3 jul
A28: CRÍTICOS — los que se han devuelto corregidos más de una vez · 11
A29: 1.1 | B29: Scope | C29: CRÍTICO | D29: Los casos del diagrama son exactamente los del Phase 1 acordado. Nada de casos extra, ni casos de fases futuras, ni procesos que se descartaron. | E29: Pipitone (client onboarding NO va), Walnut (solo voice, el AP no), Shrager (quitar Caso 3), Hudec
A30: 1.5 | B30: Nomenclatura | C30: CRÍTICO | D30: El sistema escribe "Phase 1 / Phase 2". Renombrar manualmente a "Case 1 / Case 2". No debe quedar ni una referencia nuestra a "phase". | E30: EHR Edge 16 jul; ejemplo correcto: Shrager Defense
A31: 1.8 | B31: Lógica | C31: CRÍTICO | D31: Cada condicional tiene TODAS sus salidas dibujadas, con flecha y etiqueta. No basta con describirlas en el texto lateral. | E31: QA Accuro issue #01; Hudec 28 jul (el nodo [4A-3] se quedó sin el yes path)
A32: 1.15 | B32: APIs | C32: CRÍTICO | D32: Cada API listada está verificada contra documentación oficial. Si no hay API pública, el paso se cambia a drag-and-drop / carga manual y se dice explícitamente. | E32: EHR (Cause IQ), Shrager (UJS Portal), Walnut (Quicken), Hudec (Dental Intelligence)
A33: 1.19 | B33: APIs | C33: CRÍTICO | D33: No ofrecer sistemas que no vamos a usar ni que el cliente necesita. Si ya usan Slack, las notificaciones van por Slack y por la hotlist: no se les mete SendGrid. | E33: Video Avonel 22 jun
A34: 1.20 | B34: Key Capabilities | C34: CRÍTICO | D34: Incluye siempre Scalable & Modular Architecture, redactado hacia futuros use cases, no hacia el caso actual. Ej: "Designed as a foundational system that supports future workflows, additional modules, and expanded reporting capabilities." | E34: Walnut 21 jul
A35: 1.24 | B35: TBD | C35: CRÍTICO | D35: Los TBD: pocos y agrupados. Un TBD general ("la cadencia y sus tiempos se definen con el cliente") en vez de uno por cada detalle. Demasiados TBD angustian a Alex y al cliente. | E35: Videos Avonel 22 jun
A36: 1.25 | B36: TBD | C36: CRÍTICO | D36: Lo obvio se asume, no se marca como TBD. Los detalles finos se guardan como preguntas para el cuestionario, no como TBD en el workflow. | E36: Videos Avonel 22 jun
A37: 1.27 | B37: Redacción | C37: CRÍTICO | D37: Revisar los pasos heredados de otro proyecto: nodos copiados y pegados que quedaron con el nombre del cliente anterior. | E37: Video Avonel 22 jun ("¿por qué Material Test Record Intake? Eso es de otro caso")
A38: 1.29 | B38: Redacción | C38: CRÍTICO | D38: La IA no "decide" el canal de follow-up. Redactar: "The system determines and executes the appropriate follow-up action based on the configured workflow and the contact information available for the lead." Y el contenido de los mensajes lo define y aprueba el cliente, no lo genera la IA. | E38: Recomendación de Alex, KNOWLEDGE BASE 8 jun
A39: 1.34 | B39: Plataforma | C39: CRÍTICO | D39: Verificar el PDF exportado nodo por nodo. No confiar en la vista del canvas. | E39: Walnut 16 jul
A40: SCOPE · 3
A41: 1.2 | B41: Scope | D41: Máximo 1–3 casos. 4 solo si el flujo realmente lo exige. | E41: Training Session 15 abr
A42: 1.3 | B42: Scope | D42: Todo caso cuelga de un Centralized Dashboard / AI Nucleus (LATO OS). | E42: Training Session 15 abr
A43: 1.4 | B43: Scope | D43: Lo relacionado con fees no se pone en el workflow: solo se tiene en cuenta para la proposal. | E43: Shrager 24 jul
A44: NOMENCLATURA · 1
A45: 1.6 | B45: Nomenclatura | D45: Si el cliente usa "phase" en SU proceso, no inventar términos nuevos (tipo "Lane"). Usar sub-IDs 3A / 3B / 3C: el condicional ya deja claro que son ramas. | E45: EHR Edge 16 jul
A46: ESTRUCTURA · 1
A47: 1.7 | B47: Estructura | D47: El primer nodo siempre define el intake channel: de dónde entra la data. | E47: QA Accuro, issue #02
A48: LÓGICA · 6
A49: 1.9 | B49: Lógica | D49: Todos los paths, incluidos los de salida temprana (redirects, no-match, transferencias), terminan o convergen en el nodo de logging. | E49: QA Accuro issue #03
A50: 1.10 | B50: Lógica | D50: La escalation a humano tiene su propio mini árbol de decisión: live transfer (lo pide el caller) vs. ticket / queue routing. | E50: QA Accuro issue #04
A51: 1.11 | B51: Lógica | D51: Existe el nodo final de Data Logging & Reporting. | E51: Estándar en todos los workflows
A52: 1.12 | B52: Lógica | D52: Sin nodos duplicados, sin exit paths faltantes, sin process nodes mal etiquetados. | E52: Walnut 16 jul; Pipitone 30 jul (6 issues)
A53: 1.13 | B53: Lógica | D53: La forma del nodo corresponde a lo que es: proceso, interfaz/subproceso o decisión. No usar la de interfaz para un proceso normal. | E53: Health Clinic 20 may
A54: 1.14 | B54: Lógica | D54: La numeración de nodos [1], [2A-1]… corresponde al orden real del flujo después de cada cambio. | E54: L&L 30 jun
A55: APIS · 3
A56: 1.16 | B56: APIs | D56: Ningún sistema que el cliente no haya confirmado, ni sistemas arrastrados de conversaciones viejas. | E56: Willoughby 21 jul ("¿de dónde sacaste todos estos softwares?")
A57: 1.17 | B57: APIs | D57: Todo sistema de la tabla Systems & Connections aparece en el flujo, y viceversa. | E57: Hudec 28 jul (Dental Intelligence estaba en la tabla, no en el flujo)
A58: 1.18 | B58: APIs | D58: Los sistemas fuera de scope se eliminan por completo, no se dejan mencionados. | E58: EHR (LinkedIn), Pipitone (ARIBA), Hudec (WorldPay, Dental Intelligence)
A59: KEY CAPABILITIES · 2
A60: 1.21 | B60: Key Capabilities | D60: Incluye Security & Hosting: private models, no public LLMs, data stateside (AWS/Azure), SOC 2 in progress. | E60: Estándar
A61: 1.22 | B61: Key Capabilities | D61: Se actualizan después de cualquier cambio de scope; no se quedan con las de antes. | E61: Shrager 24 jul
A62: REDACCIÓN · 4
A63: 1.23 | B63: Redacción | D63: Sin comparaciones con la versión anterior: nada de "instead of X". El workflow describe el proceso, no los cambios. | E63: L&L 30 jun
A64: 1.28 | B64: Redacción | D64: No atribuir responsabilidades ni "quién hace qué": la IA no identifica bien los roles de una reunión. | E64: Green Climate 24 jul
A65: 1.30 | B65: Redacción | D65: Preguntas clínicas, legales o de asesoría: escalation a persona, siempre. | E65: Health Clinic 18 may
A66: 1.31 | B66: Redacción | D66: La lógica de intent detection es igual en todos los casos del mismo workflow: scheduling, conversación normal, escalation. | E66: Health Clinic 18 may
A67: TBD · 1
A68: 1.26 | B68: TBD | D68: Redactar "pendiente de confirmación", no "not yet defined". | E68: Video Avonel 22 jun
A69: VISUAL · 1
A70: 1.32 | B70: Visual | D70: Textos de etiquetas cortos, para que no se solapen con las líneas del diagrama. | E70: EHR Edge 16 jul
A71: PLATAFORMA · 2
A72: 1.33 | B72: Plataforma | D72: Prompts cortos y por fases, ediciones quirúrgicas de a una. No prompts largos. | E72: Walnut 16 jul
A73: 1.35 | B73: Plataforma | D73: Aplicar a mano los ajustes que la plataforma no hace: posición de nodos, nombres, tabla de sistemas. | E73: Hudec 29 jul
A74: ENTREGA · 1
A75: 1.36 | B75: Entrega | D75: "Approve architecture" solo después de la revisión de Dana. | E75: Shrager 24 jul

Sheet 2. Proposal
A1: Proposal
A2: 62 ítems, 19 críticos. Después de que el workflow está aprobado. Nunca se construye sobre la transcript. Marca en «¿Va?» y anota en «Notas / decisión».
A4: # | B4: Categoría | C4: Crítico | D4: Qué revisar | E4: Por qué / de dónde sale | F4: ¿Va? | G4: Notas / decisión
A5: TRANSVERSALES — aplican a todos los entregables · 22
A6: T.1 | B6: Nombres | C6: CRÍTICO | D6: Cero nombres de personas, en cualquier documento: ni del cliente, ni de LATO, ni de terceros. Y cero nombres de los clientes finales o grupos del cliente. Escribir "el encargado de X". | E6: Giovanni's 28 jul ("esto lo hemos hablado mil veces"), Green Climate, Allegeant, Health Clinic
A7: T.2 | B7: Nombres | C7: CRÍTICO | D7: Nombres propios verificados, nunca copiados tal cual de la transcripción: Zelis (no Celis/Zealous), Xplor Pay (no Wordplay), Baily (no Bailey), y los grupos con su nombre completo (no apodos tipo "Gully"). | E7: Allegeant 20 jul, Hudec 28 jul, Baily 22 jul
A8: T.3 | B8: Redacción | D8: Sin guiones largos (—) en la redacción. Solo en palabras compuestas. | E8: Health Clinic 25 jun
A9: T.4 | B9: Redacción | D9: Sin emojis ni símbolos ①②③ dentro de párrafos: listas numeradas 1) 2) 3). | E9: Allegeant 20 jul, punto 4
A10: T.5 | B10: Redacción | D10: Sin referencias a grabaciones, transcripts ni reuniones. | E10: Allegeant 23 jul
A11: T.6 | B11: Redacción | D11: Sin repeticiones: ni frases duplicadas entre secciones (el generador repite "Please note: Please note:"), ni información ya dada repetida en cada paso. | E11: Baily 21 jul; video Health Clinic 16 jul
A12: T.7 | B12: Verificación | C12: CRÍTICO | D12: Lo que genera el modelo se revisa punto por punto: inventa ítems, mete temas que no se hablaron (ej. HIPAA) y afirma datos sobre terceros que no son ciertos (límites de plan, capacidades de un sistema). Solo queda lo verificado y lo que salió de la reunión. | E12: Health Clinic 16 jul; video Avonel 22 jun
A13: T.8 | B13: Verificación | C13: CRÍTICO | D13: Nada de porcentajes ni estadísticas salvo que estemos 100% seguros de que se dijeron en la reunión. "Las estadísticas son peligrosas." | E13: Video Health Clinic 16 jul
A14: T.9 | B14: Cliente | C14: CRÍTICO | D14: Nunca pedirle al cliente algo que ya confirmó en la reunión, que ya nos entregó, o a lo que ya tenemos acceso. Antes de mandar un cuestionario, cruzarlo contra la transcript. | E14: Willoughby 21 jul; Health Clinic 25 jun; video Accuro 3 jul
A15: T.10 | B15: Consistencia | C15: CRÍTICO | D15: Todo cambio se propaga en cadena: workflow → proposal → tabla de fees → key capabilities → tabla de systems & connections → timeline. | E15: River Salvage, Shrager, Walnut
A16: T.11 | B16: Archivo | D16: Antes de avisar "está listo", confirmar que el archivo guardó: revisar el timestamp de última edición. | E16: Hudec 28 jul
A17: T.12 | B17: Archivo | D17: Guardar y nombrar la versión anterior (ej. "V45 LATOAI ARCHITECT") antes de rehacer un documento o un workflow. | E17: Shrager 31 jul
A18: T.13 | B18: Entrega | D18: Entregable en Google Docs, en la carpeta correcta y con permisos de edición, link en Byron's tasks, tracker actualizado. Al compartir, confirmar en qué tab está. | E18: Shrager 24 jul; Allegeant 17 y 23 jul; Avonel 22 jun
A19: T.14 | B19: Entrega | D19: Numeración consecutiva de workflows coordinada con Dana, y proyecto creado en la plataforma con el código numérico correcto. | E19: Avonel 20 jun; Dana 14 jul
A20: T.15 | B20: Idioma | D20: Todo lo que puede leer leadership va en inglés: reportes, API research, mensajes. | E20: Green Climate 24 jul
A21: T.16 | B21: Comunicación | D21: Videos de review: varios cortos o medianos, nunca uno largo. | E21: Health Clinic 30 jul
A22: T.17 | B22: Comunicación | D22: Todo correo al cliente se lo revisa Dan antes de enviarlo. Y ojo con la zona horaria: EST va una hora adelante de la nuestra. | E22: Health Clinic, notas de voz 3 jul
A23: T.18 | B23: Posicionamiento | D23: Nunca se admite ante el cliente que los workflows se apoyan en modelos de IA abiertos. | E23: KNOWLEDGE BASE 6 abr
A24: T.19 | B24: Alcance | D24: No construimos calendar tools desde cero: se usa Calendly o Google Calendar y nos conectamos por API. | E24: KNOWLEDGE BASE 4 may
A25: T.20 | B25: Alcance | D25: Los happy paths primero: no sobrecomplicar la arquitectura sobre supuestos de una reunión de hora y media. | E25: Training Session 15 abr
A26: T.21 | B26: Proceso | D26: Si el workflow no está 100% claro, se agenda reunión solo de workflow antes de mandarlo a estimates. No vale la pena pedir pricing de un sistema que quizás no es. | E26: Training Session 15 abr
A27: T.22 | B27: Proceso | D27: Revisar support@latoai.com varias veces al día; cualquier requerimiento de cliente se le pasa a Alex, y se le confirma al cliente cuando queda resuelto. | E27: Dana 3 jul
A28: CRÍTICOS — los que se han devuelto corregidos más de una vez · 13
A29: 2.1 | B29: Orden | C29: CRÍTICO | D29: Workflow primero, proposal después. La proposal se construye sobre el workflow aprobado, no sobre la transcript. | E29: Shrager 24 jul ("¿Tamos claros? Workflow first, proposal after that")
A30: 2.14 | B30: Redacción | C30: CRÍTICO | D30: Cero "(API: X)" en el Workflow Summary y en Operational Efficiency Highlights. Se habla por canal: via SMS, via email, via voice. Los nombres y detalles de API van únicamente en API Integrations. | E30: EHR 22 jul + Baily 21 jul ("siempre me toca borrarlas a mano")
A31: 2.17 | B31: Client Confirmation | C31: CRÍTICO | D31: Solo lo que el cliente realmente tiene que dar o confirmar: accesos, licencias, credenciales, IDs, walkthroughs. Lista corta: en Baily pasó de 8 ítems a 3. | E31: Video de revisión de Baily, 22 jul
A32: 2.18 | B32: Client Confirmation | C32: CRÍTICO | D32: Fuera todo lo que gestiona LATO: Twilio, SendGrid, Webbula. Eso no se le pide al cliente. | E32: Baily 21 jul
A33: 2.19 | B33: Client Confirmation | C33: CRÍTICO | D33: Fuera las reglas de configuración interna (cadencias, fórmulas de scorecard, benchmarks, reglas de calificación, user roles & access): eso es material del cuestionario, no de la proposal. | E33: Video Baily 22 jul; video Accuro 3 jul ("el prompt da 7 y no necesitamos 7, con estas tres tenemos")
A34: 2.22 | B34: API Integrations | C34: CRÍTICO | D34: Los servicios opcionales (ej. Webbula) se describen como opcionales en todas las secciones, no como parte permanente del flujo, y no aparecen como "connectivity" ni generan requisito de API para el cliente. | E34: Video Baily 22 jul ("Webbula se muestra mucho y es opcional siempre")
A35: 2.24 | B35: Dashboard | C35: CRÍTICO | D35: Las Key capabilities son idénticas a las del workflow, no la lista que reescribe el generador. Eso incluye el bullet de Scalable & Modular Architecture. | E35: Walnut 21 jul
A36: 2.25 | B36: Terminología | C36: CRÍTICO | D36: La terminología de la proposal es la misma del workflow. Si el workflow usa "lanes", la proposal dice lanes, no cases. | E36: Video EHR 22 jul
A37: 2.31 | B37: Fees | C37: CRÍTICO | D37: El orden de las líneas sigue el orden en que leadership mandó el pricing, no el que uno prefiera. | E37: Video EHR 22 jul
A38: 2.32 | B38: Fees | C38: CRÍTICO | D38: Lo que incluye cada línea dice exactamente lo que dice el pricing. Si el bundle de leads es "unlimited communication via SMS and email", no se le agrega voice: las llamadas se facturan en su propia línea. | E38: Video EHR 22 jul
A39: 2.35 | B39: Fees | C39: CRÍTICO | D39: Formato numérico gringo: 1,000.00, miles con coma. | E39: Baily 21 jul
A40: 2.37 | B40: Fees | C40: CRÍTICO | D40: Ningún valor de template sin reemplazar: $XX,XXX.00, [X], o servicios que no aplican al caso (ej. SendGrid). | E40: Comparación template vs. entregable de Baily
A41: 2.39 | B41: Fees | C41: CRÍTICO | D41: Todo cambio en el workflow se refleja también en la tabla de fees. | E41: River Salvage 14 jul ("te quedó faltando arreglar QuickBooks en la tabla de fees")
A42: ORDEN · 3
A43: 2.2 | B43: Orden | D43: La transcript se usa solo como contexto; el scope sale del workflow. | E43: Baily 15 jul
A44: 2.3 | B44: Orden | D44: Usar los últimos prompts compartidos y generar con el modelo Max, no Lite. | E44: Baily 15 jul; Shrager 24 jul
A45: 2.4 | B45: Orden | D45: Si aún no hay pricing: dejar el emoji de precio en el título y, al llegar el precio, quitarlo y poner "- Proposal". | E45: Accuro 3 jul
A46: ESTRUCTURA · 9
A47: 2.5 | B47: Estructura | D47: Secciones completas: Project Overview · Workflow Summary · Please note · API Integrations · Client Confirmation Requirements · Centralized Dashboard · Operational Efficiency Highlights · Scope of Work · Fees · Agreement. | E47: Template LP2XXX
A48: 2.6 | B48: Estructura | D48: Títulos de casos consistentes: todos con número o todos sin número. | E48: Shrager 31 jul
A49: 2.7 | B49: Estructura | D49: Si el proyecto no tiene workflow diagram, no se titula "Workflow Summary" ni se deja el "Please note" que remite al diagrama. La redacción cambia: no es step-by-step. | E49: LAN 28 jul
A50: 2.8 | B50: Estructura | D50: Fases combinadas en un solo doc: la distinción Fase 1 / Fase 2 se mantiene en lo técnico y cada fase lleva su propio setup fee. | E50: Kovalev 21–22 jul
A51: 2.9 | B51: Estructura | D51: En una proposal combinada: una sola tabla de fees con una fila por fase, sus precios y el total de las dos, volviendo al estilo del template original con celdas mergeadas. No dos tablas separadas. | E51: Video Kovalev 22 jul
A52: 2.10 | B52: Estructura | D52: El Project Overview de una proposal combinada se replantea para explicar las dos fases juntas. El Workflow Summary sí se puede reusar de la Fase 1, con la aclaración de qué es de cada fase. | E52: Nota de voz Kovalev 21 jul
A53: 2.11 | B53: Estructura | D53: Las proposals por fases separadas se guardan como respaldo. En la carpeta de Proposals queda una sola, con el código de los dos números al final. | E53: Nota de voz Kovalev 21 jul
A54: 2.12 | B54: Estructura | D54: Intros cortas por sección: una para Fees en general (development + monthlies) y una para Setup Fees, como la de Monthly Fees. | E54: Kovalev 22 jul
A55: 2.13 | B55: Estructura | D55: Si hay fases en paralelo, ponerlo con nota explícita en el timeline. | E55: Kovalev 22 jul
A56: REDACCIÓN · 2
A57: 2.15 | B57: Redacción | D57: Nombre del cliente correcto en TODO el documento: Baily ≠ Bailey; L&L Fabrication Inc. con el punto. | E57: Baily 22 jul; L&L 30 jun
A58: 2.16 | B58: Redacción | D58: El estilo del logo del cliente no se estiliza en la proposal si el workflow no lo tiene estilizado. | E58: Accuro 3 jul
A59: API INTEGRATIONS · 3
A60: 2.20 | B60: API Integrations | D60: Solo APIs reales y confirmadas. Lo no viable se describe como manual / drag-and-drop y no aparece como integración. | E60: EHR (Cause IQ), Shrager (UJS)
A61: 2.21 | B61: API Integrations | D61: Lo dudoso se resalta en amarillo y se pregunta antes de entregar. | E61: Baily, Kovalev, Shrager
A62: 2.23 | B62: API Integrations | D62: Si el workflow menciona un canal (email, SMS, voz), la API correspondiente tiene que estar tanto en el diagrama como en la proposal. | E62: Walnut 21 jul
A63: SCOPE OF WORK · 2
A64: 2.26 | B64: Scope of Work | D64: Las 5 fases: Preparation & API Planning · Backend Development · Frontend Development · Testing & Optimization · Deployment & Client Review. | E64: Template
A65: 2.27 | B65: Scope of Work | D65: Las semanas por caso suman el total. Si el pricing no lo especifica, se confirma; no se asume. | E65: Shrager 24 jul
A66: FEES · 7
A67: 2.28 | B67: Fees | D67: Una fila de setup fee por caso (o por fase). | E67: Template LP2XXX
A68: 2.29 | B68: Fees | D68: Monthly desglosado en filas numeradas: [1] Hosting/Maintenance/Support · [2] For Calls · [3] For Leads · [4] For Chatbot Sessions, cada una con su mínimo y su tarifa de excedente. | E68: Baily, EHR, Walnut
A69: 2.30 | B69: Fees | D69: Mínimos confirmados por Mike aplicados: 400 calls · 50 leads · 200 chatbot sessions. Calls y follow-up/leads van en líneas separadas. | E69: Walnut 21 jul, Baily 21 jul, EHR 21 jul
A70: 2.33 | B70: Fees | D70: Cada línea lleva dentro de su misma fila los bullets de qué incluye: platform hosting, dashboard, support. | E70: Video EHR 22 jul
A71: 2.34 | B71: Fees | D71: Hosting/Maintenance/Support no se cotiza aparte si no hay precio: se reparte dentro de las líneas existentes. | E71: Walnut 21 jul
A72: 2.36 | B72: Fees | D72: Notas al pie completas: Active Lead Definition, qué está incluido en el fee de LATO vs. qué es client-managed, sistemas sin API (no generan fee), activación del método de pago antes de producción, contrato de 12 meses. | E72: Baily, EHR
A73: 2.38 | B73: Fees | D73: Si se elimina un caso, los sistemas que seguían usándose en otro caso se mueven de fila, no se borran. | E73: Shrager 31 jul (Clover y DocuSign)
A74: FORMATO · 1
A75: 2.40 | B75: Formato | D75: Ajustar espacios para que las secciones no queden partidas ni con textos cortos colgando al final de página. | E75: Video Baily 22 jul

Sheet 3. Technical Scope
A1: Technical Scope Document
A2: 52 ítems, 16 críticos. Antes de mandarlo a revisión. Casi todo el feedback aquí es de detalle: imágenes, capturas y formato. Marca en «¿Va?» y anota en «Notas / decisión».
A4: # | B4: Categoría | C4: Crítico | D4: Qué revisar | E4: Por qué / de dónde sale | F4: ¿Va? | G4: Notas / decisión
A5: TRANSVERSALES — aplican a todos los entregables · 22
A6: T.1 | B6: Nombres | C6: CRÍTICO | D6: Cero nombres de personas, en cualquier documento: ni del cliente, ni de LATO, ni de terceros. Y cero nombres de los clientes finales o grupos del cliente. Escribir "el encargado de X". | E6: Giovanni's 28 jul ("esto lo hemos hablado mil veces"), Green Climate, Allegeant, Health Clinic
A7: T.2 | B7: Nombres | C7: CRÍTICO | D7: Nombres propios verificados, nunca copiados tal cual de la transcripción: Zelis (no Celis/Zealous), Xplor Pay (no Wordplay), Baily (no Bailey), y los grupos con su nombre completo (no apodos tipo "Gully"). | E7: Allegeant 20 jul, Hudec 28 jul, Baily 22 jul
A8: T.3 | B8: Redacción | D8: Sin guiones largos (—) en la redacción. Solo en palabras compuestas. | E8: Health Clinic 25 jun
A9: T.4 | B9: Redacción | D9: Sin emojis ni símbolos ①②③ dentro de párrafos: listas numeradas 1) 2) 3). | E9: Allegeant 20 jul, punto 4
A10: T.5 | B10: Redacción | D10: Sin referencias a grabaciones, transcripts ni reuniones. | E10: Allegeant 23 jul
A11: T.6 | B11: Redacción | D11: Sin repeticiones: ni frases duplicadas entre secciones (el generador repite "Please note: Please note:"), ni información ya dada repetida en cada paso. | E11: Baily 21 jul; video Health Clinic 16 jul
A12: T.7 | B12: Verificación | C12: CRÍTICO | D12: Lo que genera el modelo se revisa punto por punto: inventa ítems, mete temas que no se hablaron (ej. HIPAA) y afirma datos sobre terceros que no son ciertos (límites de plan, capacidades de un sistema). Solo queda lo verificado y lo que salió de la reunión. | E12: Health Clinic 16 jul; video Avonel 22 jun
A13: T.8 | B13: Verificación | C13: CRÍTICO | D13: Nada de porcentajes ni estadísticas salvo que estemos 100% seguros de que se dijeron en la reunión. "Las estadísticas son peligrosas." | E13: Video Health Clinic 16 jul
A14: T.9 | B14: Cliente | C14: CRÍTICO | D14: Nunca pedirle al cliente algo que ya confirmó en la reunión, que ya nos entregó, o a lo que ya tenemos acceso. Antes de mandar un cuestionario, cruzarlo contra la transcript. | E14: Willoughby 21 jul; Health Clinic 25 jun; video Accuro 3 jul
A15: T.10 | B15: Consistencia | C15: CRÍTICO | D15: Todo cambio se propaga en cadena: workflow → proposal → tabla de fees → key capabilities → tabla de systems & connections → timeline. | E15: River Salvage, Shrager, Walnut
A16: T.11 | B16: Archivo | D16: Antes de avisar "está listo", confirmar que el archivo guardó: revisar el timestamp de última edición. | E16: Hudec 28 jul
A17: T.12 | B17: Archivo | D17: Guardar y nombrar la versión anterior (ej. "V45 LATOAI ARCHITECT") antes de rehacer un documento o un workflow. | E17: Shrager 31 jul
A18: T.13 | B18: Entrega | D18: Entregable en Google Docs, en la carpeta correcta y con permisos de edición, link en Byron's tasks, tracker actualizado. Al compartir, confirmar en qué tab está. | E18: Shrager 24 jul; Allegeant 17 y 23 jul; Avonel 22 jun
A19: T.14 | B19: Entrega | D19: Numeración consecutiva de workflows coordinada con Dana, y proyecto creado en la plataforma con el código numérico correcto. | E19: Avonel 20 jun; Dana 14 jul
A20: T.15 | B20: Idioma | D20: Todo lo que puede leer leadership va en inglés: reportes, API research, mensajes. | E20: Green Climate 24 jul
A21: T.16 | B21: Comunicación | D21: Videos de review: varios cortos o medianos, nunca uno largo. | E21: Health Clinic 30 jul
A22: T.17 | B22: Comunicación | D22: Todo correo al cliente se lo revisa Dan antes de enviarlo. Y ojo con la zona horaria: EST va una hora adelante de la nuestra. | E22: Health Clinic, notas de voz 3 jul
A23: T.18 | B23: Posicionamiento | D23: Nunca se admite ante el cliente que los workflows se apoyan en modelos de IA abiertos. | E23: KNOWLEDGE BASE 6 abr
A24: T.19 | B24: Alcance | D24: No construimos calendar tools desde cero: se usa Calendly o Google Calendar y nos conectamos por API. | E24: KNOWLEDGE BASE 4 may
A25: T.20 | B25: Alcance | D25: Los happy paths primero: no sobrecomplicar la arquitectura sobre supuestos de una reunión de hora y media. | E25: Training Session 15 abr
A26: T.21 | B26: Proceso | D26: Si el workflow no está 100% claro, se agenda reunión solo de workflow antes de mandarlo a estimates. No vale la pena pedir pricing de un sistema que quizás no es. | E26: Training Session 15 abr
A27: T.22 | B27: Proceso | D27: Revisar support@latoai.com varias veces al día; cualquier requerimiento de cliente se le pasa a Alex, y se le confirma al cliente cuando queda resuelto. | E27: Dana 3 jul
A28: CRÍTICOS — los que se han devuelto corregidos más de una vez · 10
A29: 3.1 | B29: Estructura | C29: CRÍTICO | D29: Un solo documento, una sola tab, un solo PDF, aunque cubra dos procesos distintos. Se divide en secciones internas, nunca en documentos separados. | E29: Allegeant 17 jul (nota de voz)
A30: 3.6 | B30: Contenido | C30: CRÍTICO | D30: Cada afirmación técnica verificada. ¿De verdad es WordPress? ¿De verdad está en Hostinger? ¿De verdad existe ese sistema de encriptación? No convertir en hecho un comentario o un chiste del cliente. | E30: Health Clinic 25 jun; Allegeant 20 jul, punto 13
A31: 3.9 | B31: Contenido | C31: CRÍTICO | D31: Los intervalos de sincronización llevan nota de dependencia de la API del proveedor: no podemos garantizarlos. | E31: Health Clinic 25 jun
A32: 3.11 | B32: Contenido | C32: CRÍTICO | D32: Los pasos que ejecuta una persona se declaran explícitamente: el sistema notifica a la persona encargada; el sistema no envía ese correo. | E32: Allegeant 20 jul, punto 6
A33: 3.17 | B33: Imágenes | C33: CRÍTICO | D33: Las imágenes son solo imágenes: cero texto o explicaciones dentro de la imagen. Los devs necesitan el doc en .md y ese texto se pierde. Toda explicación va en el cuerpo del paso; si la imagen ya trae texto, se rehace. | E33: Allegeant 20 jul, punto 3
A34: 3.20 | B34: Imágenes | C34: CRÍTICO | D34: Las señalizaciones (flechas, círculos, números) apuntan al elemento correcto. | E34: Allegeant 20 jul, punto 9
A35: 3.22 | B35: Imágenes | C35: CRÍTICO | D35: Legibilidad: los números y campos se leen. Si la fuente (grabación del notetaker) tiene mala calidad, se vuelve a capturar. | E35: Allegeant 20 jul, punto 11
A36: 3.24 | B36: Formato | C36: CRÍTICO | D36: Título y texto de la figura quedan juntos. Usar page break cuando la imagen los separa. | E36: Allegeant 20 jul, punto 5
A37: 3.25 | B37: Formato | C37: CRÍTICO | D37: Sin títulos ni textos huérfanos al final de página. | E37: Health Clinic 25 jun
A38: 3.29 | B38: Formato | C38: CRÍTICO | D38: Los niveles de heading empiezan en Heading 1, no en Heading 2, y de ahí se usa la extensión de numeración. El modelo suele arrancar en H2 y descuadra toda la jerarquía. | E38: Video Health Clinic 25 jun
A39: ESTRUCTURA · 4
A40: 3.2 | B40: Estructura | D40: Cubre el proceso completo acordado (ej. martes Y viernes), con el contexto de qué se hace cada día. | E40: Allegeant 17 jul
A41: 3.3 | B41: Estructura | D41: La longitud no es problema: es un tech scope, va todo lo importante. | E41: Health Clinic 25 jun
A42: 3.4 | B42: Estructura | D42: Secciones tipo: Purpose & Scope · Application Architecture (auth, data source, sync) · Reference Source · Portal Structure · módulo por módulo · Cross-Module Data Relationships · Data Accuracy & Rebuild Plan · Assumptions & Client Confirmations · Out of Scope. | E42: Health Clinic Ph2
A43: 3.5 | B43: Estructura | D43: Si cambia la estructura del doc, la intro y el overview se actualizan también. | E43: Health Clinic 25 jun
A44: CONTENIDO · 8
A45: 3.7 | B45: Contenido | D45: Todos los portales y roles documentados (Admin, Sales Rep, Partners), ninguno omitido, cada uno con sus capturas. | E45: Health Clinic 25 jun
A46: 3.8 | B46: Contenido | D46: Conceptos parecidos bien diferenciados: SSO vs. individual login. | E46: Health Clinic 25 jun
A47: 3.10 | B47: Contenido | D47: Incluir un módulo de estado de sincronización visible para el cliente: última actualización, errores, reintentos. Referencia: Stambrosky. | E47: Health Clinic 25 jun
A48: 3.12 | B48: Contenido | D48: Las reglas que dependen de un cheat sheet del cliente se declaran como tal, con captura de la hoja. Nada de tablas presentadas como información cierta: mejor bulletpoints de ejemplo. | E48: Allegeant 20 jul, punto 8
A49: 3.13 | B49: Contenido | D49: Los wizards se documentan completos, pantalla por pantalla, sin saltarse pasos. | E49: Allegeant 20 jul punto 12 y 23 jul
A50: 3.14 | B50: Contenido | D50: Las referencias cruzadas ("see 3") existen de verdad. | E50: Allegeant 20 jul, punto 13
A51: 3.15 | B51: Contenido | D51: Cada sección al nivel de detalle correcto: si algo queda corto (ej. el assembly del package), se amplía con más capturas. | E51: Allegeant 20 jul, punto 7
A52: 3.16 | B52: Contenido | D52: No afirmar cosas técnicamente falsas por simplificar. Si hay una alternativa, va como nota, no como afirmación. | E52: Video Health Clinic 16 jul (los leads sí se podrían leer desde Practice Better: de ahí vienen los correos)
A53: IMÁGENES · 4
A54: 3.18 | B54: Imágenes | D54: Cada figura numerada, con título, ubicada en el paso que ilustra. | E54: Allegeant
A55: 3.19 | B55: Imágenes | D55: Una captura por paso. No combinar varios pasos en una sola imagen. | E55: Allegeant 23 jul
A56: 3.21 | B56: Imágenes | D56: La captura corresponde al proceso descrito en ese paso. | E56: Allegeant 20 jul, punto 10
A57: 3.23 | B57: Imágenes | D57: Si faltan pantallas del proceso, se vuelven a capturar: en el check wizard había más interfaces. | E57: Allegeant 20 jul, punto 12
A58: FORMATO · 4
A59: 3.26 | B59: Formato | D59: Las tablas no se parten entre páginas. | E59: Health Clinic 25 jun
A60: 3.27 | B60: Formato | D60: Estilo de encabezados de tabla consistente: todas con azul o todas sin color, no mezclado. | E60: Health Clinic 25 jun
A61: 3.28 | B61: Formato | D61: Fuente y tamaño consistentes en todo el documento. | E61: Health Clinic 25 jun
A62: 3.30 | B62: Formato | D62: Espaciado parejo entre secciones: ni bloques pegados ni huecos gigantes entre headings. | E62: Video Health Clinic 25 jun

Sheet 4. API Research
A1: API Research Report
A2: 30 ítems, 8 críticos. Antes de pasarlo a Dana o a Mike. Alimenta directamente al workflow y a la proposal. Marca en «¿Va?» y anota en «Notas / decisión».
A4: # | B4: Categoría | C4: Crítico | D4: Qué revisar | E4: Por qué / de dónde sale | F4: ¿Va? | G4: Notas / decisión
A5: TRANSVERSALES — aplican a todos los entregables · 22
A6: T.1 | B6: Nombres | C6: CRÍTICO | D6: Cero nombres de personas, en cualquier documento: ni del cliente, ni de LATO, ni de terceros. Y cero nombres de los clientes finales o grupos del cliente. Escribir "el encargado de X". | E6: Giovanni's 28 jul ("esto lo hemos hablado mil veces"), Green Climate, Allegeant, Health Clinic
A7: T.2 | B7: Nombres | C7: CRÍTICO | D7: Nombres propios verificados, nunca copiados tal cual de la transcripción: Zelis (no Celis/Zealous), Xplor Pay (no Wordplay), Baily (no Bailey), y los grupos con su nombre completo (no apodos tipo "Gully"). | E7: Allegeant 20 jul, Hudec 28 jul, Baily 22 jul
A8: T.3 | B8: Redacción | D8: Sin guiones largos (—) en la redacción. Solo en palabras compuestas. | E8: Health Clinic 25 jun
A9: T.4 | B9: Redacción | D9: Sin emojis ni símbolos ①②③ dentro de párrafos: listas numeradas 1) 2) 3). | E9: Allegeant 20 jul, punto 4
A10: T.5 | B10: Redacción | D10: Sin referencias a grabaciones, transcripts ni reuniones. | E10: Allegeant 23 jul
A11: T.6 | B11: Redacción | D11: Sin repeticiones: ni frases duplicadas entre secciones (el generador repite "Please note: Please note:"), ni información ya dada repetida en cada paso. | E11: Baily 21 jul; video Health Clinic 16 jul
A12: T.7 | B12: Verificación | C12: CRÍTICO | D12: Lo que genera el modelo se revisa punto por punto: inventa ítems, mete temas que no se hablaron (ej. HIPAA) y afirma datos sobre terceros que no son ciertos (límites de plan, capacidades de un sistema). Solo queda lo verificado y lo que salió de la reunión. | E12: Health Clinic 16 jul; video Avonel 22 jun
A13: T.8 | B13: Verificación | C13: CRÍTICO | D13: Nada de porcentajes ni estadísticas salvo que estemos 100% seguros de que se dijeron en la reunión. "Las estadísticas son peligrosas." | E13: Video Health Clinic 16 jul
A14: T.9 | B14: Cliente | C14: CRÍTICO | D14: Nunca pedirle al cliente algo que ya confirmó en la reunión, que ya nos entregó, o a lo que ya tenemos acceso. Antes de mandar un cuestionario, cruzarlo contra la transcript. | E14: Willoughby 21 jul; Health Clinic 25 jun; video Accuro 3 jul
A15: T.10 | B15: Consistencia | C15: CRÍTICO | D15: Todo cambio se propaga en cadena: workflow → proposal → tabla de fees → key capabilities → tabla de systems & connections → timeline. | E15: River Salvage, Shrager, Walnut
A16: T.11 | B16: Archivo | D16: Antes de avisar "está listo", confirmar que el archivo guardó: revisar el timestamp de última edición. | E16: Hudec 28 jul
A17: T.12 | B17: Archivo | D17: Guardar y nombrar la versión anterior (ej. "V45 LATOAI ARCHITECT") antes de rehacer un documento o un workflow. | E17: Shrager 31 jul
A18: T.13 | B18: Entrega | D18: Entregable en Google Docs, en la carpeta correcta y con permisos de edición, link en Byron's tasks, tracker actualizado. Al compartir, confirmar en qué tab está. | E18: Shrager 24 jul; Allegeant 17 y 23 jul; Avonel 22 jun
A19: T.14 | B19: Entrega | D19: Numeración consecutiva de workflows coordinada con Dana, y proyecto creado en la plataforma con el código numérico correcto. | E19: Avonel 20 jun; Dana 14 jul
A20: T.15 | B20: Idioma | D20: Todo lo que puede leer leadership va en inglés: reportes, API research, mensajes. | E20: Green Climate 24 jul
A21: T.16 | B21: Comunicación | D21: Videos de review: varios cortos o medianos, nunca uno largo. | E21: Health Clinic 30 jul
A22: T.17 | B22: Comunicación | D22: Todo correo al cliente se lo revisa Dan antes de enviarlo. Y ojo con la zona horaria: EST va una hora adelante de la nuestra. | E22: Health Clinic, notas de voz 3 jul
A23: T.18 | B23: Posicionamiento | D23: Nunca se admite ante el cliente que los workflows se apoyan en modelos de IA abiertos. | E23: KNOWLEDGE BASE 6 abr
A24: T.19 | B24: Alcance | D24: No construimos calendar tools desde cero: se usa Calendly o Google Calendar y nos conectamos por API. | E24: KNOWLEDGE BASE 4 may
A25: T.20 | B25: Alcance | D25: Los happy paths primero: no sobrecomplicar la arquitectura sobre supuestos de una reunión de hora y media. | E25: Training Session 15 abr
A26: T.21 | B26: Proceso | D26: Si el workflow no está 100% claro, se agenda reunión solo de workflow antes de mandarlo a estimates. No vale la pena pedir pricing de un sistema que quizás no es. | E26: Training Session 15 abr
A27: T.22 | B27: Proceso | D27: Revisar support@latoai.com varias veces al día; cualquier requerimiento de cliente se le pasa a Alex, y se le confirma al cliente cuando queda resuelto. | E27: Dana 3 jul
A28: CRÍTICOS — los que se han devuelto corregidos más de una vez · 2
A29: 4.1 | B29: Método | C29: CRÍTICO | D29: Solo fuentes oficiales y actuales. Nunca el knowledge base propio del modelo. | E29: Prompt oficial, KNOWLEDGE BASE 6 abr
A30: 4.4 | B30: Contenido | C30: CRÍTICO | D30: Reportar las posibilidades encontradas, no dar recomendaciones ni asumir el approach. Si falta info, se reporta "se necesita contactar al vendor" y ya. | E30: Green Climate 24 jul
A31: CONTENIDO · 5
A32: 4.2 | B32: Contenido | D32: Responder siempre las cuatro preguntas: ¿existe API pública? ¿hay sandbox? ¿cómo se obtienen las keys de producción y de sandbox, requiere partner o aprobación? ¿hay costo o suscripción extra? | E32: Prompt oficial
A33: 4.3 | B33: Contenido | D33: Veredicto explícito: viable · requiere validación con el vendor · no viable. | E33: Ejemplos Foundation / McCormick / Trimble
A34: 4.5 | B34: Contenido | D34: Incluir las preguntas concretas para el vendor y sus datos de contacto. | E34: Green Climate, Giovanni's
A35: 4.6 | B35: Contenido | D35: Declarar qué parte del scope queda TBD mientras el vendor no responda. | E35: Green Climate, Giovanni's
A36: 4.7 | B36: Contenido | D36: Si la API no existe: definir la alternativa (drag & drop, CSV, middleware) y actualizar workflow y proposal. | E36: EHR (Cause IQ), Shrager (UJS)
A37: PROCESO · 1
A38: 4.8 | B38: Proceso | D38: Primero email con preguntas puntuales al vendor. Reunión solo si ellos la piden o no responden por escrito. | E38: KNOWLEDGE BASE 23 abr

Sheet 5. Business Logic
A1: Business Logic Doc / Designer Brief
A2: 37 ítems, 8 críticos. Antes de entregárselo a Alex o al equipo de diseño. Marca en «¿Va?» y anota en «Notas / decisión».
A4: # | B4: Categoría | C4: Crítico | D4: Qué revisar | E4: Por qué / de dónde sale | F4: ¿Va? | G4: Notas / decisión
A5: TRANSVERSALES — aplican a todos los entregables · 22
A6: T.1 | B6: Nombres | C6: CRÍTICO | D6: Cero nombres de personas, en cualquier documento: ni del cliente, ni de LATO, ni de terceros. Y cero nombres de los clientes finales o grupos del cliente. Escribir "el encargado de X". | E6: Giovanni's 28 jul ("esto lo hemos hablado mil veces"), Green Climate, Allegeant, Health Clinic
A7: T.2 | B7: Nombres | C7: CRÍTICO | D7: Nombres propios verificados, nunca copiados tal cual de la transcripción: Zelis (no Celis/Zealous), Xplor Pay (no Wordplay), Baily (no Bailey), y los grupos con su nombre completo (no apodos tipo "Gully"). | E7: Allegeant 20 jul, Hudec 28 jul, Baily 22 jul
A8: T.3 | B8: Redacción | D8: Sin guiones largos (—) en la redacción. Solo en palabras compuestas. | E8: Health Clinic 25 jun
A9: T.4 | B9: Redacción | D9: Sin emojis ni símbolos ①②③ dentro de párrafos: listas numeradas 1) 2) 3). | E9: Allegeant 20 jul, punto 4
A10: T.5 | B10: Redacción | D10: Sin referencias a grabaciones, transcripts ni reuniones. | E10: Allegeant 23 jul
A11: T.6 | B11: Redacción | D11: Sin repeticiones: ni frases duplicadas entre secciones (el generador repite "Please note: Please note:"), ni información ya dada repetida en cada paso. | E11: Baily 21 jul; video Health Clinic 16 jul
A12: T.7 | B12: Verificación | C12: CRÍTICO | D12: Lo que genera el modelo se revisa punto por punto: inventa ítems, mete temas que no se hablaron (ej. HIPAA) y afirma datos sobre terceros que no son ciertos (límites de plan, capacidades de un sistema). Solo queda lo verificado y lo que salió de la reunión. | E12: Health Clinic 16 jul; video Avonel 22 jun
A13: T.8 | B13: Verificación | C13: CRÍTICO | D13: Nada de porcentajes ni estadísticas salvo que estemos 100% seguros de que se dijeron en la reunión. "Las estadísticas son peligrosas." | E13: Video Health Clinic 16 jul
A14: T.9 | B14: Cliente | C14: CRÍTICO | D14: Nunca pedirle al cliente algo que ya confirmó en la reunión, que ya nos entregó, o a lo que ya tenemos acceso. Antes de mandar un cuestionario, cruzarlo contra la transcript. | E14: Willoughby 21 jul; Health Clinic 25 jun; video Accuro 3 jul
A15: T.10 | B15: Consistencia | C15: CRÍTICO | D15: Todo cambio se propaga en cadena: workflow → proposal → tabla de fees → key capabilities → tabla de systems & connections → timeline. | E15: River Salvage, Shrager, Walnut
A16: T.11 | B16: Archivo | D16: Antes de avisar "está listo", confirmar que el archivo guardó: revisar el timestamp de última edición. | E16: Hudec 28 jul
A17: T.12 | B17: Archivo | D17: Guardar y nombrar la versión anterior (ej. "V45 LATOAI ARCHITECT") antes de rehacer un documento o un workflow. | E17: Shrager 31 jul
A18: T.13 | B18: Entrega | D18: Entregable en Google Docs, en la carpeta correcta y con permisos de edición, link en Byron's tasks, tracker actualizado. Al compartir, confirmar en qué tab está. | E18: Shrager 24 jul; Allegeant 17 y 23 jul; Avonel 22 jun
A19: T.14 | B19: Entrega | D19: Numeración consecutiva de workflows coordinada con Dana, y proyecto creado en la plataforma con el código numérico correcto. | E19: Avonel 20 jun; Dana 14 jul
A20: T.15 | B20: Idioma | D20: Todo lo que puede leer leadership va en inglés: reportes, API research, mensajes. | E20: Green Climate 24 jul
A21: T.16 | B21: Comunicación | D21: Videos de review: varios cortos o medianos, nunca uno largo. | E21: Health Clinic 30 jul
A22: T.17 | B22: Comunicación | D22: Todo correo al cliente se lo revisa Dan antes de enviarlo. Y ojo con la zona horaria: EST va una hora adelante de la nuestra. | E22: Health Clinic, notas de voz 3 jul
A23: T.18 | B23: Posicionamiento | D23: Nunca se admite ante el cliente que los workflows se apoyan en modelos de IA abiertos. | E23: KNOWLEDGE BASE 6 abr
A24: T.19 | B24: Alcance | D24: No construimos calendar tools desde cero: se usa Calendly o Google Calendar y nos conectamos por API. | E24: KNOWLEDGE BASE 4 may
A25: T.20 | B25: Alcance | D25: Los happy paths primero: no sobrecomplicar la arquitectura sobre supuestos de una reunión de hora y media. | E25: Training Session 15 abr
A26: T.21 | B26: Proceso | D26: Si el workflow no está 100% claro, se agenda reunión solo de workflow antes de mandarlo a estimates. No vale la pena pedir pricing de un sistema que quizás no es. | E26: Training Session 15 abr
A27: T.22 | B27: Proceso | D27: Revisar support@latoai.com varias veces al día; cualquier requerimiento de cliente se le pasa a Alex, y se le confirma al cliente cuando queda resuelto. | E27: Dana 3 jul
A28: CRÍTICOS — los que se han devuelto corregidos más de una vez · 2
A29: 5.1 | B29: Nivel de detalle | C29: CRÍTICO | D29: No es un technical scope. Es una lista de cositas a tener en cuenta: título, descripción corta, lenguaje muy simple, sin exagerar ni pedir de más. Formato tipo Buffalo Valley, no tipo Witkowski. | E29: Health Clinic, notas de voz 16 jul
A30: 5.5 | B30: Audiencia | C30: CRÍTICO | D30: Escribir para quien lo va a leer. Si es para devs, no explicarles lo que ya saben (que la IA habla en lenguaje natural, cómo funciona un CRM board); sí explicarles lo que no saben (que el costo es por paciente, que todo queda logueado). | E30: Videos Health Clinic 16 jul
A31: CONTENIDO · 3
A32: 5.2 | B32: Contenido | D32: Recoge la lógica de negocio que se habló en la reunión y que la plataforma debe cumplir: ventanas horarias de notificación, zonas horarias por estado, reglas de escalación, cadencias por paciente o cliente, toggles de on/off. | E32: Health Clinic 16 jul
A33: 5.3 | B33: Contenido | D33: Cada regla que implique una interfaz describe esa interfaz (ej. la bandeja de escalaciones con su campo de respuesta y su botón de enviar al provider), con screenshot de referencia cuando exista. | E33: Health Clinic 16 jul
A34: 5.4 | B34: Contenido | D34: Screenshots solo donde apliquen. Lo que se habló y no tiene pantalla va solo en texto. | E34: Health Clinic 16 jul
A35: ESTRUCTURA · 4
A36: 5.6 | B36: Estructura | D36: En briefs de plataforma se organiza por módulos o tabs, con una intro que explique qué módulos trae cada fase. | E36: Witkowski 13 jul
A37: 5.7 | B37: Estructura | D37: Cada módulo lleva sus tres pantallas: lista, detalle y formulario de creación, con sus campos. | E37: Witkowski 13 jul
A38: 5.8 | B38: Estructura | D38: No exagerar en campos. Si hay duda, dejarlos como no obligatorios. La idea es plataformas simples para el cliente. | E38: Witkowski 13 jul
A39: 5.9 | B39: Estructura | D39: Dividir por fases para que la revisión (interna y con el cliente) sea por partes y no una sola tanda enorme. | E39: Witkowski 13 jul
A40: USO · 1
A41: 5.10 | B41: Uso | D41: Sirve también como memoria interna: dentro de meses volvemos a él para entender cómo funciona el negocio del cliente. Escribirlo pensando en eso. | E41: Health Clinic 16 jul
A42: PRECISIÓN · 3
A43: 5.11 | B43: Precisión | D43: Las reglas se declaran al nivel de granularidad correcto: per patient, per medication, no "por paciente" a secas, cuando una misma factura trae varios medicamentos con periodos distintos. | E43: Video Health Clinic 16 jul
A44: 5.12 | B44: Precisión | D44: Los canales que NO usamos no se mencionan. Si el caso no hace voz, no aparece voz en ninguna parte. | E44: Video Health Clinic 16 jul
A45: 5.13 | B45: Precisión | D45: No inventar aprobaciones ni confirmaciones con terceros que no tienen que ver con ese punto. | E45: Video Health Clinic 16 jul
A46: REQUERIMIENTOS · 1
A47: 5.14 | B47: Requerimientos | D47: Los cambios pedidos a Alex van con screenshot y el requerimiento concreto (estilo Martik / Buffalo Valley), no en prosa. Si no se les dice exactamente dónde está el cambio, no lo encuentran. | E47: Willoughby 3 jul; River Salvage 14 jul
A48: PROTOTIPOS · 1
A49: 5.15 | B49: Prototipos | D49: Al revisar un prototipo contra la arquitectura: comparar campo por campo contra el ejemplo de referencia (Stambrosky), confirmar que existe la interfaz de sincronización de cada integración, que las facturas se pueden cargar, ver y editar (manual entry no es digitar todo), y que hay dashboard de reportes. Usar la terminología del cliente: subcontractors, no vendors. | E49: Videos Willoughby 3 jul

Sheet T. Transversales (fuente)
A1: TRANSVERSALES — fuente única
A2: Estas 22 reglas se repiten como primer bloque en cada pestaña de documento. Se editan en data/transversales.json y se regeneran con build/build_data.py y build/build_xlsx.py.
A4: # | B4: Categoría | C4: Crítico | D4: Qué revisar | E4: Por qué / de dónde sale
A5: T.1 | B5: Nombres | C5: CRÍTICO | D5: Cero nombres de personas, en cualquier documento: ni del cliente, ni de LATO, ni de terceros. Y cero nombres de los clientes finales o grupos del cliente. Escribir "el encargado de X". | E5: Giovanni's 28 jul ("esto lo hemos hablado mil veces"), Green Climate, Allegeant, Health Clinic
A6: T.2 | B6: Nombres | C6: CRÍTICO | D6: Nombres propios verificados, nunca copiados tal cual de la transcripción: Zelis (no Celis/Zealous), Xplor Pay (no Wordplay), Baily (no Bailey), y los grupos con su nombre completo (no apodos tipo "Gully"). | E6: Allegeant 20 jul, Hudec 28 jul, Baily 22 jul
A7: T.3 | B7: Redacción | D7: Sin guiones largos (—) en la redacción. Solo en palabras compuestas. | E7: Health Clinic 25 jun
A8: T.4 | B8: Redacción | D8: Sin emojis ni símbolos ①②③ dentro de párrafos: listas numeradas 1) 2) 3). | E8: Allegeant 20 jul, punto 4
A9: T.5 | B9: Redacción | D9: Sin referencias a grabaciones, transcripts ni reuniones. | E9: Allegeant 23 jul
A10: T.6 | B10: Redacción | D10: Sin repeticiones: ni frases duplicadas entre secciones (el generador repite "Please note: Please note:"), ni información ya dada repetida en cada paso. | E10: Baily 21 jul; video Health Clinic 16 jul
A11: T.7 | B11: Verificación | C11: CRÍTICO | D11: Lo que genera el modelo se revisa punto por punto: inventa ítems, mete temas que no se hablaron (ej. HIPAA) y afirma datos sobre terceros que no son ciertos (límites de plan, capacidades de un sistema). Solo queda lo verificado y lo que salió de la reunión. | E11: Health Clinic 16 jul; video Avonel 22 jun
A12: T.8 | B12: Verificación | C12: CRÍTICO | D12: Nada de porcentajes ni estadísticas salvo que estemos 100% seguros de que se dijeron en la reunión. "Las estadísticas son peligrosas." | E12: Video Health Clinic 16 jul
A13: T.9 | B13: Cliente | C13: CRÍTICO | D13: Nunca pedirle al cliente algo que ya confirmó en la reunión, que ya nos entregó, o a lo que ya tenemos acceso. Antes de mandar un cuestionario, cruzarlo contra la transcript. | E13: Willoughby 21 jul; Health Clinic 25 jun; video Accuro 3 jul
A14: T.10 | B14: Consistencia | C14: CRÍTICO | D14: Todo cambio se propaga en cadena: workflow → proposal → tabla de fees → key capabilities → tabla de systems & connections → timeline. | E14: River Salvage, Shrager, Walnut
A15: T.11 | B15: Archivo | D15: Antes de avisar "está listo", confirmar que el archivo guardó: revisar el timestamp de última edición. | E15: Hudec 28 jul
A16: T.12 | B16: Archivo | D16: Guardar y nombrar la versión anterior (ej. "V45 LATOAI ARCHITECT") antes de rehacer un documento o un workflow. | E16: Shrager 31 jul
A17: T.13 | B17: Entrega | D17: Entregable en Google Docs, en la carpeta correcta y con permisos de edición, link en Byron's tasks, tracker actualizado. Al compartir, confirmar en qué tab está. | E17: Shrager 24 jul; Allegeant 17 y 23 jul; Avonel 22 jun
A18: T.14 | B18: Entrega | D18: Numeración consecutiva de workflows coordinada con Dana, y proyecto creado en la plataforma con el código numérico correcto. | E18: Avonel 20 jun; Dana 14 jul
A19: T.15 | B19: Idioma | D19: Todo lo que puede leer leadership va en inglés: reportes, API research, mensajes. | E19: Green Climate 24 jul
A20: T.16 | B20: Comunicación | D20: Videos de review: varios cortos o medianos, nunca uno largo. | E20: Health Clinic 30 jul
A21: T.17 | B21: Comunicación | D21: Todo correo al cliente se lo revisa Dan antes de enviarlo. Y ojo con la zona horaria: EST va una hora adelante de la nuestra. | E21: Health Clinic, notas de voz 3 jul
A22: T.18 | B22: Posicionamiento | D22: Nunca se admite ante el cliente que los workflows se apoyan en modelos de IA abiertos. | E22: KNOWLEDGE BASE 6 abr
A23: T.19 | B23: Alcance | D23: No construimos calendar tools desde cero: se usa Calendly o Google Calendar y nos conectamos por API. | E23: KNOWLEDGE BASE 4 may
A24: T.20 | B24: Alcance | D24: Los happy paths primero: no sobrecomplicar la arquitectura sobre supuestos de una reunión de hora y media. | E24: Training Session 15 abr
A25: T.21 | B25: Proceso | D25: Si el workflow no está 100% claro, se agenda reunión solo de workflow antes de mandarlo a estimates. No vale la pena pedir pricing de un sistema que quizás no es. | E25: Training Session 15 abr
A26: T.22 | B26: Proceso | D26: Revisar support@latoai.com varias veces al día; cualquier requerimiento de cliente se le pasa a Alex, y se le confirma al cliente cuando queda resuelto. | E26: Dana 3 jul
